aidge_export_tensorrt/__init__.py
aidge_export_tensorrt/generate_plugin.py
aidge_export_tensorrt/operators.py
aidge_export_tensorrt/static/tensorrt_10.10/CMakeLists.txt
aidge_export_tensorrt/static/tensorrt_10.10/Makefile
aidge_export_tensorrt/static/tensorrt_10.10/README.md
aidge_export_tensorrt/static/tensorrt_10.10/main.cpp
aidge_export_tensorrt/static/tensorrt_10.10/test.py
aidge_export_tensorrt/static/tensorrt_10.10/cmake/FindCUDAToolkit.cmake
aidge_export_tensorrt/static/tensorrt_10.10/cmake/FindCuDNN.cmake
aidge_export_tensorrt/static/tensorrt_10.10/cmake/FindTensorRT.cmake
aidge_export_tensorrt/static/tensorrt_10.10/include/BatchStream.hpp
aidge_export_tensorrt/static/tensorrt_10.10/include/Graph.hpp
aidge_export_tensorrt/static/tensorrt_10.10/include/IInt8EntropyCalibrator.hpp
aidge_export_tensorrt/static/tensorrt_10.10/include/Utils.hpp
aidge_export_tensorrt/static/tensorrt_10.10/include/cuda_utils.h
aidge_export_tensorrt/static/tensorrt_10.10/python_binding/pybind_export.cpp
aidge_export_tensorrt/static/tensorrt_10.10/src/Graph.cpp
aidge_export_tensorrt/static/tensorrt_10.10/tools/compile_export_linux.sh
aidge_export_tensorrt/static/tensorrt_10.10/tools/docker-entrypoint.sh
aidge_export_tensorrt/static/tensorrt_10.10/tools/tensorrt10.10_compiler.Dockerfile
aidge_export_tensorrt/static/tensorrt_8.6/CMakeLists.txt
aidge_export_tensorrt/static/tensorrt_8.6/Makefile
aidge_export_tensorrt/static/tensorrt_8.6/README.md
aidge_export_tensorrt/static/tensorrt_8.6/main.cpp
aidge_export_tensorrt/static/tensorrt_8.6/test.py
aidge_export_tensorrt/static/tensorrt_8.6/cmake/FindCUDAToolkit.cmake
aidge_export_tensorrt/static/tensorrt_8.6/cmake/FindCuDNN.cmake
aidge_export_tensorrt/static/tensorrt_8.6/cmake/FindTensorRT.cmake
aidge_export_tensorrt/static/tensorrt_8.6/include/BatchStream.hpp
aidge_export_tensorrt/static/tensorrt_8.6/include/Graph.hpp
aidge_export_tensorrt/static/tensorrt_8.6/include/IInt8EntropyCalibrator.hpp
aidge_export_tensorrt-0.2.2.dist-info/licenses/LICENSE
aidge_export_tensorrt-0.2.2.dist-info/METADATA
aidge_export_tensorrt-0.2.2.dist-info/WHEEL
aidge_export_tensorrt-0.2.2.dist-info/top_level.txt
aidge_export_tensorrt-0.2.2.dist-info/RECORD
