Metadata-Version: 2.4
Name: aidge_export_tensorrt
Version: 0.2.2
Summary:  Aidge Export TensorRT
Platform: Linux
Classifier: Development Status :: 2 - Pre-Alpha
Requires-Python: >=3.7
License-File: LICENSE
Dynamic: classifier
Dynamic: description-content-type
Dynamic: license-file
Dynamic: platform
Dynamic: requires-python
Dynamic: summary
